{
    "popularityCurve": {
        "data": [
            1,
            1
        ],
        "xLabels": [
            "01:46",
            "03:18"
        ],
        "label": {
            "phrase": "we make sure they get their food fast and they have a good time while they're here",
            "count": 1
        }
    },
    "clusterList": [
        {
            "phrase": "we make sure they get their food fast and they have a good time while they're here",
            "count": 1
        },
        {
            "phrase": "man how long is it gonna take for them to get our pizza i'm starvin i never ate my dang toast",
            "count": 1
        }
    ]
}