{
    "popularityCurve": {
        "data": [
            1
        ],
        "xLabels": [
            "00:28"
        ],
        "label": {
            "phrase": "i think i see where you're going with all this it's not my cup of hot toddy but i might know a guy or gal i'll ask around may i give you one piece of advice blog diva if i promise not to rain on your blog parade",
            "count": 1
        }
    },
    "clusterList": [
        {
            "phrase": "i think i see where you're going with all this it's not my cup of hot toddy but i might know a guy or gal i'll ask around may i give you one piece of advice blog diva if i promise not to rain on your blog parade",
            "count": 1
        }
    ]
}