{
    "popularityCurve": {
        "data": [
            1,
            2
        ],
        "xLabels": [
            "04:21",
            "04:23"
        ],
        "label": {
            "phrase": "but i've never done it as much as now doing a mural is big-and it's going to be up for a year",
            "count": 1
        }
    },
    "clusterList": [
        {
            "phrase": "but i've never done it as much as now doing a mural is big-and it's going to be up for a year",
            "count": 1
        },
        {
            "phrase": "we have a number of extraordinary painters and the russian school of art is one of the best i always felt sorry i could not pursue art as a profession",
            "count": 1
        },
        {
            "phrase": "unfortunately not i went to study physics and languages and there was nobody around me interested in art i got support from my mum i have to explain that there were no free venues for artists in the soviet era to display one's work there were exhibitions only for artists who were part of the artists union supervised by the state there was no freedom of expressing yourself poor artists could not sell their work could not show it to anybody when perestroika happened i must admit there was a rapid change in freeing of the arts the first sign of this was a vernissage an exhibiton of art and craft in the park in moscow i guess it is like montmartre so in moscow it is the arbat street it was so extraordinary that little freedom that artists gained",
            "count": 1
        }
    ]
}