{
    "popularityCurve": {
        "data": [
            1,
            1,
            1
        ],
        "xLabels": [
            "01:52",
            "03:27",
            "03:48"
        ],
        "label": "graph expo's value to attendees lies in the opportunity it provides to not only evaluate the latest graphic communications technology first-hand on the show floor but also to learn in our many educational sessions how to apply them to gain the greatest business success"
    },
    "clusterList": [
        {
            "phrase": "graph expo's value to attendees lies in the opportunity it provides to not only evaluate the latest graphic communications technology first-hand on the show floor but also to learn in our many educational sessions how to apply them to gain the greatest business success",
            "count": 2
        },
        {
            "phrase": "the expo will help everyone from consumers to companies to learn",
            "count": 1
        }
    ]
}