{
    "popularityCurve": {
        "data": [
            1,
            1,
            1,
            1,
            1
        ],
        "xLabels": [
            "01:48",
            "02:01",
            "02:14",
            "02:18",
            "03:19"
        ],
        "label": "so the procedure is done without that being verified often causing problems in sex"
    },
    "clusterList": [
        {
            "phrase": "so the procedure is done without that being verified often causing problems in sex",
            "count": 4
        },
        {
            "phrase": "the problem is not with the procedure but the way it is abused by men so that men think they are now immune from hiv contagion",
            "count": 1
        }
    ]
}