{
    "popularityCurve": {
        "data": [
            2
        ],
        "xLabels": [
            "02:39"
        ],
        "label": "you know learn how to summon a premonition i mean cecile does she even uses spells sometimes"
    },
    "clusterList": [
        {
            "phrase": "you know learn how to summon a premonition i mean cecile does she even uses spells sometimes",
            "count": 1
        },
        {
            "phrase": "and i doubt that cecile's control over her own premonitions is that great besides i tried it once some four years ago and it didn't work",
            "count": 1
        }
    ]
}