{
    "popularityCurve": {
        "data": [
            1
        ],
        "xLabels": [
            "04:12"
        ],
        "label": {
            "phrase": "shall not require a multiple regression analysis or anecdotal evidence for a compensation discrimination case",
            "count": 1
        }
    },
    "clusterList": [
        {
            "phrase": "shall not require a multiple regression analysis or anecdotal evidence for a compensation discrimination case",
            "count": 1
        }
    ]
}