{
    "popularityCurve": {
        "data": [
            1,
            1,
            1,
            1,
            1,
            1,
            3,
            1,
            1,
            1,
            1,
            1,
            1,
            1
        ],
        "xLabels": [
            "00:00",
            "00:01",
            "00:09",
            "00:53",
            "01:00",
            "01:29",
            "02:08",
            "02:38",
            "02:43",
            "04:03",
            "04:33",
            "04:40",
            "04:49",
            "04:50"
        ],
        "label": "we're"
    },
    "clusterList": [
        {
            "phrase": "but with the dry fuel conditions that we have throughout the state we could see similar situations arise again until we get a significant amount of rain",
            "count": 5
        },
        {
            "phrase": "we're looking to transitions to monsoons next week",
            "count": 1
        },
        {
            "phrase": "because we've been so stormy it's kind of kept us out of the heat the forecast for the next two days takes us up into the lower 90s when we get into that warmer weather that's an indication that stream has moved to the north",
            "count": 1
        },
        {
            "phrase": "are we really going to take off in a nasty thunderstorm",
            "count": 1
        },
        {
            "phrase": "we just need some time to recover even though it looks like we could get a bit more rain at the weekend this was a really bad pattern that hit us twice",
            "count": 1
        },
        {
            "phrase": "there's an outside chance we could see some showers and thunderstorms in the middle of next week and that could knock our temperatures down a bit",
            "count": 1
        },
        {
            "phrase": "but for the next several days at least we expect temperatures near or above 100",
            "count": 1
        },
        {
            "phrase": "it will be a little more humid this weekend",
            "count": 1
        },
        {
            "phrase": "drier winter months coupled with the low humidity and gusty westerly winds which traditionally arrive at this time of year increase the threat of bushfire",
            "count": 1
        },
        {
            "phrase": "rain rain go away you can come back at 930 am on sunday",
            "count": 1
        },
        {
            "phrase": "and we're going to be full steam ahead as soon as the warmer weather hits",
            "count": 1
        },
        {
            "phrase": "if the weather is good then we would expect to see jupiter",
            "count": 1
        }
    ]
}