{
    "popularityCurve": {
        "data": [
            1
        ],
        "xLabels": [
            "02:20"
        ],
        "label": {
            "phrase": "this legislation is exactly what titus says she is supporting the question is how many democrats can my opponent get",
            "count": 1
        }
    },
    "clusterList": [
        {
            "phrase": "this legislation is exactly what titus says she is supporting the question is how many democrats can my opponent get",
            "count": 1
        }
    ]
}