{
    "popularityCurve": {
        "data": [
            1,
            1,
            1,
            1,
            1
        ],
        "xLabels": [
            "01:50",
            "02:28",
            "04:22",
            "04:23",
            "04:44"
        ],
        "label": "if"
    },
    "clusterList": [
        {
            "phrase": "if endeavor had been an investor rather than an independent objective non-profit enabler it would not have been trusted by the business elite or the entrepreneurs",
            "count": 1
        },
        {
            "phrase": "we believe the board is independent and focused on value creation for long-term shareholders legg mason chairman bill miller said at the time",
            "count": 1
        },
        {
            "phrase": "for that reason it threatens a company's shareholders in a very direct way",
            "count": 1
        },
        {
            "phrase": "google inc is working on plans to start a venture-capital arm according to several people briefed on the discussions",
            "count": 1
        },
        {
            "phrase": "google has long invested in promising start-ups so the news that the company was thinking about formalizing those efforts by creating a venture-capital arm reported in the wall street journal thursday was hardly surprising a person familiar with google's plans who spoke on condition of anonymity because he was not authorized to discuss them confirmed that the company had hired william maris a 33-year-old former entrepreneur and investor to explore the idea of a venture arm but the person said that at this point the effort is embryonic at best there is no structure no organization and no capital assigned to the project and it is possible that mr maris will end up working on other projects",
            "count": 1
        }
    ]
}