{
    "popularityCurve": {
        "data": [
            1
        ],
        "xLabels": [
            "01:25"
        ],
        "label": {
            "phrase": "powerful magnet s for scholars and donors who share a specific set of interests and values to the exclusion of others whether this is openly acknowledged or not",
            "count": 1
        }
    },
    "clusterList": [
        {
            "phrase": "powerful magnet s for scholars and donors who share a specific set of interests and values to the exclusion of others whether this is openly acknowledged or not",
            "count": 1
        }
    ]
}