{
    "popularityCurve": {
        "data": [
            1
        ],
        "xLabels": [
            "01:37"
        ],
        "label": {
            "phrase": "how can they make us pay if the contract is under the name of the usa and we are known as something else like america or bushland",
            "count": 1
        }
    },
    "clusterList": [
        {
            "phrase": "how can they make us pay if the contract is under the name of the usa and we are known as something else like america or bushland",
            "count": 1
        }
    ]
}