{
    "popularityCurve": {
        "data": [
            1
        ],
        "xLabels": [
            "01:14"
        ],
        "label": {
            "phrase": "we are children of the fire made of it and only the same divinity transmuted and at two or three removes when we know least about it",
            "count": 1
        }
    },
    "clusterList": [
        {
            "phrase": "we are children of the fire made of it and only the same divinity transmuted and at two or three removes when we know least about it",
            "count": 1
        }
    ]
}