{
    "popularityCurve": {
        "data": [
            1,
            1,
            1
        ],
        "xLabels": [
            "04:21",
            "04:46",
            "04:55"
        ],
        "label": "thanks the port authority for promoting transit usage on regional systems in conjunction with its own services"
    },
    "clusterList": [
        {
            "phrase": "thanks the port authority for promoting transit usage on regional systems in conjunction with its own services",
            "count": 3
        }
    ]
}