{
    "popularityCurve": {
        "data": [
            1,
            1,
            1
        ],
        "xLabels": [
            "01:20",
            "02:02",
            "02:09"
        ],
        "label": "what does he mean by literally all the other players puke i wish you were still a washing machine"
    },
    "clusterList": [
        {
            "phrase": "what does he mean by literally all the other players puke i wish you were still a washing machine",
            "count": 3
        }
    ]
}