{
    "popularityCurve": {
        "data": [
            1
        ],
        "xLabels": [
            "03:46"
        ],
        "label": {
            "phrase": "it's simply not plausible to say you favor border enforcement and then oppose all of the actual steps needed to have the border enforced",
            "count": 1
        }
    },
    "clusterList": [
        {
            "phrase": "it's simply not plausible to say you favor border enforcement and then oppose all of the actual steps needed to have the border enforced",
            "count": 1
        }
    ]
}