{
    "popularityCurve": {
        "data": [
            1
        ],
        "xLabels": [
            "00:15"
        ],
        "label": "i cannot describe for you the wailing the tearing the uncontrolled sobbing that now took place in our house for what seemed like eternity"
    },
    "clusterList": [
        {
            "phrase": "i cannot describe for you the wailing the tearing the uncontrolled sobbing that now took place in our house for what seemed like eternity",
            "count": 1
        }
    ]
}