{
    "popularityCurve": {
        "data": [
            1
        ],
        "xLabels": [
            "05:00"
        ],
        "label": "jane hello dear yes of course it's judith listen dear i need to call a meeting of the club yes that's it exactly no no details until later well if you're put out i just can't help that ciao darling"
    },
    "clusterList": [
        {
            "phrase": "jane hello dear yes of course it's judith listen dear i need to call a meeting of the club yes that's it exactly no no details until later well if you're put out i just can't help that ciao darling",
            "count": 1
        }
    ]
}