{
    "popularityCurve": {
        "data": [
            1
        ],
        "xLabels": [
            "00:16"
        ],
        "label": {
            "phrase": "whilst acquisition of the land near pheasant wood for a permanent war cemetery is a commonwealth war graves commission responsibility we acknowledge the generous offer of land by the owner of the mass burial site madame demassiet and will consider the needs of all parties including the tenant farmer in this process",
            "count": 1
        }
    },
    "clusterList": [
        {
            "phrase": "whilst acquisition of the land near pheasant wood for a permanent war cemetery is a commonwealth war graves commission responsibility we acknowledge the generous offer of land by the owner of the mass burial site madame demassiet and will consider the needs of all parties including the tenant farmer in this process",
            "count": 1
        }
    ]
}