{
    "popularityCurve": {
        "data": [
            1
        ],
        "xLabels": [
            "04:37"
        ],
        "label": {
            "phrase": "the people putting this thing together should be applauded because they truly have raised the level each year of the entertainment they've provided",
            "count": 1
        }
    },
    "clusterList": [
        {
            "phrase": "the people putting this thing together should be applauded because they truly have raised the level each year of the entertainment they've provided",
            "count": 1
        }
    ]
}