{
    "popularityCurve": {
        "data": [
            1
        ],
        "xLabels": [
            "01:20"
        ],
        "label": {
            "phrase": "mia and i are going to have fun in the fun forest she's too serious her shrink has prescribed fun therapy for her please mind the stand for a while please sell a few berries as well as eating them",
            "count": 1
        }
    },
    "clusterList": [
        {
            "phrase": "mia and i are going to have fun in the fun forest she's too serious her shrink has prescribed fun therapy for her please mind the stand for a while please sell a few berries as well as eating them",
            "count": 1
        }
    ]
}