{
    "popularityCurve": {
        "data": [
            1
        ],
        "xLabels": [
            "04:50"
        ],
        "label": {
            "phrase": "taken an instant liking to her because she is visible and direct and informal without turning informality into a cloying down-home soupiness",
            "count": 1
        }
    },
    "clusterList": [
        {
            "phrase": "taken an instant liking to her because she is visible and direct and informal without turning informality into a cloying down-home soupiness",
            "count": 1
        }
    ]
}