{
    "popularityCurve": {
        "data": [
            1,
            1,
            2,
            2,
            1,
            2,
            11,
            2,
            1,
            2,
            1,
            1,
            1,
            1,
            1,
            1,
            1,
            4,
            1,
            1,
            1,
            1,
            1,
            1,
            2,
            2,
            1,
            2,
            1,
            2,
            1,
            1,
            1,
            2,
            1,
            2,
            2
        ],
        "xLabels": [
            "00:09",
            "00:12",
            "00:20",
            "00:22",
            "00:28",
            "00:29",
            "00:53",
            "01:00",
            "01:01",
            "01:19",
            "01:21",
            "01:40",
            "01:42",
            "01:46",
            "01:47",
            "01:52",
            "02:10",
            "02:14",
            "02:20",
            "02:26",
            "02:33",
            "02:36",
            "02:38",
            "03:05",
            "03:06",
            "03:09",
            "03:11",
            "03:34",
            "03:44",
            "04:10",
            "04:13",
            "04:19",
            "04:28",
            "04:37",
            "04:38",
            "04:41",
            "05:00"
        ],
        "label": {
            "phrase": "simple guide to setting up your blog",
            "count": 10
        }
    },
    "clusterList": [
        {
            "phrase": "simple guide to setting up your blog",
            "count": 10
        },
        {
            "phrase": "i'm working on several ways to abuse twitter as a platform and i'll publish my research in this blog when i'm done",
            "count": 5
        },
        {
            "phrase": "reaching beyond your blog using social networking sites and twitter",
            "count": 3
        },
        {
            "phrase": "blogging while brown",
            "count": 2
        },
        {
            "phrase": "for example i made a pdf of today's digg homepage that includes links to no less than three",
            "count": 2
        },
        {
            "phrase": "if you have a great article that is somehow buried in your archives of your blog that might relate dig it out dust it off and submit it",
            "count": 2
        },
        {
            "phrase": "i am used to db just repackaging wsj articles and making posts out of them to pass the time but ep too",
            "count": 2
        },
        {
            "phrase": "i haven't blogged in a while",
            "count": 1
        },
        {
            "phrase": "i will not read blogs i'm sorry if something is important enough it will be brought to my attention",
            "count": 1
        },
        {
            "phrase": "bootstrapping blog owner overview and article overview",
            "count": 1
        },
        {
            "phrase": "small business blogging 10 reasons why its essential to business growth",
            "count": 1
        },
        {
            "phrase": "101 tips secrets from successful bloggers",
            "count": 1
        },
        {
            "phrase": "what no one ever tells you about blogging and podcasting real life advice from 101 bloggers",
            "count": 1
        },
        {
            "phrase": "since blogs have no history i can only extrapolate a value proposition from the recent past and from the present",
            "count": 1
        },
        {
            "phrase": "iphone therefore i blog",
            "count": 1
        },
        {
            "phrase": "has blogging lost its relational focus",
            "count": 1
        },
        {
            "phrase": "how to comment on someone's blog",
            "count": 1
        },
        {
            "phrase": "a lap of the blogs",
            "count": 1
        },
        {
            "phrase": "lap of the blogs",
            "count": 1
        },
        {
            "phrase": "enhance literacy by ensuring that each student maintains his her own blog by the end of the school year and posts entries at least once per month",
            "count": 1
        },
        {
            "phrase": "what is the next hot blog topic",
            "count": 1
        },
        {
            "phrase": "blogging is the best medium yet for the voice of the people it is helping to make changes in policy and is essentially keeping government transparent finally the people have a voice and some long awaited power",
            "count": 1
        },
        {
            "phrase": "how do you balance your blog with real life",
            "count": 1
        },
        {
            "phrase": "navigating the financial blogosphere how to benefit from free information on the internet",
            "count": 1
        },
        {
            "phrase": "discover the insider blog traffic secrets guaranteed to bring you floods of free website visitors on demand",
            "count": 1
        },
        {
            "phrase": "create build a blog",
            "count": 1
        },
        {
            "phrase": "thursday night basset blogging",
            "count": 1
        },
        {
            "phrase": "insert your spotplex code in your blog you can also find how many people read your articles",
            "count": 1
        },
        {
            "phrase": "find most visited blog artcles today",
            "count": 1
        },
        {
            "phrase": "you can even set a page to be the home page for your blog so it's the first thing readers see when they go to your url",
            "count": 1
        },
        {
            "phrase": "a blogologist who is constantly raising the bar for interest and variety",
            "count": 1
        },
        {
            "phrase": "walking the berkshires a traditional weblog if there is such a thing",
            "count": 1
        },
        {
            "phrase": "one of the truly unique efforts in the christian blogosphere",
            "count": 1
        },
        {
            "phrase": "authors seeking publicity turn to virtual blog tours for attention",
            "count": 1
        },
        {
            "phrase": "we identified five or six blogs where we felt we'd give it a try",
            "count": 1
        },
        {
            "phrase": "blog with us",
            "count": 1
        },
        {
            "phrase": "will give our on-line audience easy entree to a dozen or so of the good blogs produced by lehigh valley folks",
            "count": 1
        },
        {
            "phrase": "for bloglines we want to do a",
            "count": 1
        },
        {
            "phrase": "blogs are powerful tools to support creative writing that can be published and shared not only with the teacher but also with peers and the world alike",
            "count": 1
        },
        {
            "phrase": "the blog editing system in action",
            "count": 1
        },
        {
            "phrase": "what blogging needs to be saved",
            "count": 1
        },
        {
            "phrase": "plurk twitter and blog",
            "count": 1
        },
        {
            "phrase": "we're all about rss and channeling information from blogs wikis forums and other kinds of channels into feed-enabled portals",
            "count": 1
        }
    ]
}