{
    "popularityCurve": {
        "data": [
            1,
            1
        ],
        "xLabels": [
            "01:09",
            "04:01"
        ],
        "label": "i had a loss a couple years ago they adjusted at 75 and it wasn't nearly as bad as this i'm thinking this area of the field west of the yard here is probably at least 80 or better between 80 and 100 you know so"
    },
    "clusterList": [
        {
            "phrase": "i had a loss a couple years ago they adjusted at 75 and it wasn't nearly as bad as this i'm thinking this area of the field west of the yard here is probably at least 80 or better between 80 and 100 you know so",
            "count": 1
        },
        {
            "phrase": "i just thought doing 60 feet was a lot better it was a drastic change to go from baseball to slow-pitch softball but after a couple of weeks i got adjusted",
            "count": 1
        }
    ]
}