{
    "popularityCurve": {
        "data": [
            1
        ],
        "xLabels": [
            "05:05"
        ],
        "label": "while many evangelicals celebrated cassie bernall and rachel scott as martyrs who died for their christian convictions at columbine high school i wonder if we will extend the same heroism to the victims in tennessee"
    },
    "clusterList": [
        {
            "phrase": "while many evangelicals celebrated cassie bernall and rachel scott as martyrs who died for their christian convictions at columbine high school i wonder if we will extend the same heroism to the victims in tennessee",
            "count": 1
        }
    ]
}