{
    "popularityCurve": {
        "data": [
            1
        ],
        "xLabels": [
            "04:29"
        ],
        "label": "i've seen what may be the best futuristic anthology series since the glory days of the twilight zone and the outer limits it's called masters of science fiction"
    },
    "clusterList": [
        {
            "phrase": "i've seen what may be the best futuristic anthology series since the glory days of the twilight zone and the outer limits it's called masters of science fiction",
            "count": 1
        }
    ]
}